jupyterStyle/StyleHelper.py
jupyterStyle/__init__.py
jupyterStyle/style_template.css_template
jupyter_style-1.1.2.dist-info/LICENSE
jupyter_style-1.1.2.dist-info/METADATA
jupyter_style-1.1.2.dist-info/WHEEL
jupyter_style-1.1.2.dist-info/top_level.txt
jupyter_style-1.1.2.dist-info/RECORD
