Metadata-Version: 2.1
Name: jupyter-style
Version: 1.1.2
Summary: This is style generator, you can simply generate inline css to insert into your Jupyter notebook to change look of tables in your preview. 
Home-page: https://github.com/RobertOlechowski/Jupyter-Style
Author: Robert Olechowski
Author-email: RobertOlechowski@gmail.com
License: MIT
Platform: UNKNOWN
Classifier: Programming Language :: Python :: 3
Classifier: License :: OSI Approved :: MIT License
Classifier: Operating System :: OS Independent
